[{
"fk_servidor": 2,
"apelido": "DESKTOP-G2ODTKO",
"captura": 11157037.00,
"minutos": 0,
"classificacao": "OK"
},{
"fk_servidor": 4,
"apelido": "DESKTOP-K5L8ML3",
"captura": 84775689.00,
"minutos": 0,
"classificacao": "OK"
},{
"fk_servidor": 5,
"apelido": "DESKTOP-886AGFM",
"captura": 21023321.00,
"minutos": 0,
"classificacao": "OK"
},{
"fk_servidor": 6,
"apelido": "DESKTOP-HMMLF0T",
"captura": 202300213.00,
"minutos": 0,
"classificacao": "OK"
},{
"fk_servidor": 7,
"apelido": "DESKTOP-21227JH",
"captura": 27646798.00,
"minutos": 0,
"classificacao": "OK"
},{
"fk_servidor": 8,
"apelido": "DESKTOP-3N4TKBA",
"captura": 0.00,
"minutos": 103,
"classificacao": "CRITICO"
}]